pyl7plot/__init__.py
pyl7plot/engine.py
pyl7plot/meta.py
pyl7plot/plot.py
pyl7plot/helper/__init__.py
pyl7plot/helper/code.py
pyl7plot/helper/file.py
pyl7plot/helper/html.py
pyl7plot/templates/jupyter-lab.html
pyl7plot/templates/notebook.html
pyl7plot/templates/plot.html
pyl7plot-0.0.5.dist-info/LICENSE
pyl7plot-0.0.5.dist-info/METADATA
pyl7plot-0.0.5.dist-info/WHEEL
pyl7plot-0.0.5.dist-info/top_level.txt
pyl7plot-0.0.5.dist-info/RECORD
