Metadata-Version: 2.1
Name: pyl7plot
Version: 0.0.5
Summary: Python3 binding for @AntV/L7Plot Plotting Library, make charting easier.
Home-page: https://github.com/lvisei/pyl7plot
Author: @lvisei
Author-email: yunji.me@outlook.com
License: MIT
Keywords: AntV,L7Plot,charts,PyL7Plot,visualization,map,geospatial-visualization
Platform: UNKNOWN
Classifier: Environment :: Console
Classifier: Intended Audience :: Developers
Classifier: License :: OSI Approved :: MIT License
Classifier: Operating System :: OS Independent
Classifier: Programming Language :: Python
Classifier: Programming Language :: Python :: 3
Classifier: Programming Language :: Python :: 3.6
Classifier: Programming Language :: Python :: 3.7
Classifier: Programming Language :: Python :: 3.8
Classifier: Programming Language :: Python :: 3.9
Classifier: Topic :: Software Development :: Libraries
License-File: LICENSE
Requires-Dist: jinja2 (~=2.11.3)
Requires-Dist: simplejson
